pydad/__init__.py
pydad/binary_search.py
pydad/bubble_sort.py
pydad/min_max.py
pydad/selection_sort.py
pydad/sequential_search.py
pydad-0.0.3.dist-info/DESCRIPTION.rst
pydad-0.0.3.dist-info/METADATA
pydad-0.0.3.dist-info/RECORD
pydad-0.0.3.dist-info/WHEEL
pydad-0.0.3.dist-info/metadata.json
pydad-0.0.3.dist-info/top_level.txt
