Metadata-Version: 2.0
Name: pydad
Version: 0.0.3
Summary: Data structure, Algorithm and Design pattern written in python.
Home-page: https://github.com/crazy-canux/pydad
Author: Canux CHENG
Author-email: canuxcheng@gmail.com
License: GPL
Keywords: python algorithm
Platform: any
Classifier: Development Status :: 5 - Production/Stable
Classifier: Environment :: Console
Classifier: Intended Audience :: Developers
Classifier: Natural Language :: English
Classifier: License :: OSI Approved :: GNU General Public License (GPL)
Classifier: Operating System :: POSIX
Classifier: Programming Language :: Python
Classifier: Programming Language :: Python :: 2.7
Classifier: Topic :: Software Development :: Libraries :: Python Modules
